titanscraper/__init__.py
titanscraper/config.py
titanscraper/processors.py
titanscraper/titanscraper.py
titanscraper/utils.py
titanscraper-0.0.21.dist-info/LICENSE
titanscraper-0.0.21.dist-info/METADATA
titanscraper-0.0.21.dist-info/WHEEL
titanscraper-0.0.21.dist-info/top_level.txt
titanscraper-0.0.21.dist-info/RECORD
