Metadata-Version: 2.1
Name: titanscraper
Version: 0.0.21
Summary: A web scraping library that makes web-scraping easy
Home-page: https://github.com/emileKing/titanscraper
Author: Emile DJIDA GONGDEBIYA
Author-email: djidadevacc@gmail.com
License: MIT
Platform: UNKNOWN
Classifier: Development Status :: 3 - Alpha
Classifier: Intended Audience :: Developers
Classifier: Topic :: Software Development :: Build Tools
Classifier: Programming Language :: Python :: 3.8
Classifier: Programming Language :: Python :: 3.9
Classifier: Programming Language :: Python :: 3.10
License-File: LICENSE
Requires-Dist: beautifulsoup4 (==4.10.0)
Requires-Dist: xmltodict (==0.12.0)
Requires-Dist: lxml
Requires-Dist: requests (==2.26.0)
